berita_indonesia/__init__.py
News_Indonesia-0.1.dist-info/LICENSE
News_Indonesia-0.1.dist-info/METADATA
News_Indonesia-0.1.dist-info/WHEEL
News_Indonesia-0.1.dist-info/top_level.txt
News_Indonesia-0.1.dist-info/RECORD
