Metadata-Version: 2.1
Name: News-Indonesia
Version: 0.1
Summary: This package will display various news in Indenesia
Home-page: https://github.com/Reinz-Stuff/News-Indonesia
Author: Fauzi Kurniawan
Author-email: fauzik354313@gmail.com
Project-URL: Github, https://github.com/Reinz-Stuff
Classifier: Programming Language :: Python :: 3
Classifier: License :: OSI Approved :: GNU General Public License v3 (GPLv3)
Classifier: Operating System :: OS Independent
Classifier: Development Status :: 4 - Beta
Requires-Python: >=3.6
License-File: LICENSE
